{"inkVersion":21,"root":[["ev","str","^Shade","/str","/ev",{"VAR=":"speaker","re":true},"^I noticed Evelyn isn't in your family photo. Oversight or intentional?","\n","ev","str","^Victor","/str","/ev",{"VAR=":"speaker","re":true},"^That photo was taken during... a difficult time. Families, Detective, are rarely as picturesque as we like to imagine. Surely you've seen worse in your line of work.","\n","ev","str","^Shade","/str","/ev",{"VAR=":"speaker","re":true},"^You had issues with her, didn't you? Enough to pressure her into changing her will?","\n","ev","str","^Victor","/str","/ev",{"VAR=":"speaker","re":true},"^I had my disagreements with Evelyn, yes. But family disagreements are hardly a crime, are they? Someone had to ensure the business survived her... whims.","\n","end",["done",{"#f":5,"#n":"g-0"}],null],"done",{"global decl":["ev","str","^Victor","/str",{"VAR=":"speaker"},"str","^Normal","/str",{"VAR=":"mood"},"/ev","end",null],"#f":1}],"listDefs":{}}